pytest_django_dotenv/__init__.py
pytest_django_dotenv/plugin.py
pytest_django_dotenv-0.1.2.dist-info/LICENSE
pytest_django_dotenv-0.1.2.dist-info/METADATA
pytest_django_dotenv-0.1.2.dist-info/WHEEL
pytest_django_dotenv-0.1.2.dist-info/entry_points.txt
pytest_django_dotenv-0.1.2.dist-info/top_level.txt
pytest_django_dotenv-0.1.2.dist-info/RECORD
